odoo/addons/account_tax_group_widget_base_amount/README.rst
odoo/addons/account_tax_group_widget_base_amount/__init__.py
odoo/addons/account_tax_group_widget_base_amount/__manifest__.py
odoo/addons/account_tax_group_widget_base_amount/i18n/account_tax_group_widget_base_amount.pot
odoo/addons/account_tax_group_widget_base_amount/i18n/de.po
odoo/addons/account_tax_group_widget_base_amount/i18n/es.po
odoo/addons/account_tax_group_widget_base_amount/i18n/it.po
odoo/addons/account_tax_group_widget_base_amount/readme/CONTRIBUTORS.rst
odoo/addons/account_tax_group_widget_base_amount/readme/DESCRIPTION.rst
odoo/addons/account_tax_group_widget_base_amount/static/description/account_tax_group_widget_base_amount.png
odoo/addons/account_tax_group_widget_base_amount/static/description/icon.png
odoo/addons/account_tax_group_widget_base_amount/static/description/index.html
odoo/addons/account_tax_group_widget_base_amount/static/src/xml/tax_group.xml
odoo_addon_account_tax_group_widget_base_amount-16.0.1.0.0.9.dist-info/METADATA
odoo_addon_account_tax_group_widget_base_amount-16.0.1.0.0.9.dist-info/WHEEL
odoo_addon_account_tax_group_widget_base_amount-16.0.1.0.0.9.dist-info/top_level.txt
odoo_addon_account_tax_group_widget_base_amount-16.0.1.0.0.9.dist-info/RECORD
